equality/__init__.py
equality/equality.py
equality-0.1.1.dist-info/DESCRIPTION.rst
equality-0.1.1.dist-info/METADATA
equality-0.1.1.dist-info/RECORD
equality-0.1.1.dist-info/WHEEL
equality-0.1.1.dist-info/metadata.json
equality-0.1.1.dist-info/top_level.txt
equality-0.1.1.dist-info/zip-safe
