Metadata-Version: 2.0
Name: equality
Version: 0.1.1
Summary: Utilities to aid in testing for equality.
Home-page: http://pypi.python.org/pypi/equality/
Author: Jonathan Hartley
Author-email: tartley@tartley.com
License: UNKNOWN
Keywords: test testing equal equals equality
Platform: UNKNOWN
Classifier: Development Status :: 4 - Beta
Classifier: Environment :: Console
Classifier: Intended Audience :: Developers
Classifier: License :: OSI Approved :: BSD License
Classifier: Natural Language :: English
Classifier: Operating System :: OS Independent
Classifier: Programming Language :: Python :: 2
Classifier: Programming Language :: Python :: 2.7
Classifier: Programming Language :: Python :: 3
Classifier: Programming Language :: Python :: 3.4
Classifier: Programming Language :: Python :: Implementation :: CPython
Requires-Dist: pendulum (==1.3.2)
